<?xml version="1.0" encoding="utf-8" ?>

<percentile>
    <object>
        <lower>1</lower>
        <content>Rod of lesser metamagic: Enlarge,0</content>
        <upper>7</upper>
    </object>
    <object>
        <lower>8</lower>
        <content>Rod of lesser metamagic: Extend,0</content>
        <upper>14</upper>
    </object>
    <object>
        <lower>15</lower>
        <content>Rod of lesser metamagic: Silent,0</content>
        <upper>21</upper>
    </object>
    <object>
        <lower>22</lower>
        <content>Immovable rod,0</content>
        <upper>28</upper>
    </object>
    <object>
        <lower>29</lower>
        <content>Rod of lesser metamagic: Empower,0</content>
        <upper>35</upper>
    </object>
    <object>
        <lower>36</lower>
        <content>Rod of metal and mineral detection,0</content>
        <upper>42</upper>
    </object>
    <object>
        <lower>43</lower>
        <content>Rod of cancellation,0</content>
        <upper>53</upper>
    </object>
    <object>
        <lower>54</lower>
        <content>Rod of metamagic: Enlarge,0</content>
        <upper>57</upper>
    </object>
    <object>
        <lower>58</lower>
        <content>Rod of metamagic: Extend,0</content>
        <upper>61</upper>
    </object>
    <object>
        <lower>62</lower>
        <content>Rod of metamagic: Silent,0</content>
        <upper>65</upper>
    </object>
    <object>
        <lower>66</lower>
        <content>Rod of wonder,0</content>
        <upper>71</upper>
    </object>
    <object>
        <lower>72</lower>
        <content>Rod of the python,1</content>
        <upper>79</upper>
    </object>
    <object>
        <lower>80</lower>
        <content>Rod of lesser metamagic: Maximize,0</content>
        <upper>83</upper>
    </object>
    <object>
        <lower>84</lower>
        <content>Rod of flame extinguishing,0</content>
        <upper>89</upper>
    </object>
    <object>
        <lower>90</lower>
        <content>Rod of the viper,2</content>
        <upper>97</upper>
    </object>
    <object>
        <lower>98</lower>
        <content>Rod of metamagic: Empower,0</content>
        <upper>99</upper>
    </object>
    <object>
        <lower>100</lower>
        <content>Rod of lesser metamagic: Quicken,0</content>
        <upper>100</upper>
    </object>
</percentile>