<?xml version="1.0" encoding="utf-8" ?>

<collections>
    <collection>
        <name>12</name>
        <entry>30 ft. vision and hearing</entry>
        <entry>1</entry>
        <entry>0</entry>
    </collection>
    <collection>
        <name>13</name>
        <entry>60 ft. vision and hearing</entry>
        <entry>2</entry>
        <entry>0</entry>
    </collection>
    <collection>
        <name>14</name>
        <entry>120 ft. vision and hearing</entry>
        <entry>2</entry>
        <entry>0</entry>
    </collection>
    <collection>
        <name>15</name>
        <entry>60 ft. darkvision and hearing</entry>
        <entry>3</entry>
        <entry>0</entry>
    </collection>
    <collection>
        <name>16</name>
        <entry>60 ft. darkvision and hearing</entry>
        <entry>3</entry>
        <entry>0</entry>
    </collection>
    <collection>
        <name>17</name>
        <entry>120 ft. darkvision and hearing</entry>
        <entry>3</entry>
        <entry>1</entry>
    </collection>
    <collection>
        <name>18</name>
        <entry>120 ft. darkvision, blindsense, and hearing</entry>
        <entry>3</entry>
        <entry>2</entry>
    </collection>
    <collection>
        <name>19</name>
        <entry>120 ft. darkvision, blindsense, and hearing</entry>
        <entry>4</entry>
        <entry>3</entry>
    </collection>
</collections>