<?xml version="1.0" encoding="utf-8" ?>

<collections>
    <collection>
        <name>ReplacementStrings</name>
        <entry>DESIGNATEDFOE</entry>
        <entry>GENDER</entry>
        <entry>HEIGHT</entry>
        <entry>KNOWLEDGECATEGORY</entry>
        <entry>ENERGY</entry>
        <entry>PARTIALALIGNMENT</entry>
        <entry>FULLALIGNMENT</entry>
    </collection>
    <collection>
        <name>DESIGNATEDFOE</name>
        <entry>DesignatedFoes</entry>
    </collection>
    <collection>
        <name>GENDER</name>
        <entry>Gender</entry>
    </collection>
    <collection>
        <name>HEIGHT</name>
        <entry>CurseHeightChanges</entry>
    </collection>
    <collection>
        <name>KNOWLEDGECATEGORY</name>
        <entry>KnowledgeCategories</entry>
    </collection>
    <collection>
        <name>ENERGY</name>
        <entry>Elements</entry>
    </collection>
    <collection>
        <name>PARTIALALIGNMENT</name>
        <entry>PartialAlignments</entry>
    </collection>
    <collection>
        <name>FULLALIGNMENT</name>
        <entry>FullAlignments</entry>
    </collection>
</collections>